README.rst
setup.cfg
setup.py
requests_f5auth/__init__.py
requests_f5auth/exceptions.py
requests_f5auth/utils.py
requests_f5auth/xf5_auth.py
requests_f5auth.egg-info/PKG-INFO
requests_f5auth.egg-info/SOURCES.txt
requests_f5auth.egg-info/dependency_links.txt
requests_f5auth.egg-info/not-zip-safe
requests_f5auth.egg-info/requires.txt
requests_f5auth.egg-info/top_level.txt